fastapi_tryton_integration/__init__.py
fastapi_tryton_integration/fastapi_tryton.py
fastapi_tryton_integration-2.0.4.dist-info/licenses/LICENSE
fastapi_tryton_integration-2.0.4.dist-info/METADATA
fastapi_tryton_integration-2.0.4.dist-info/WHEEL
fastapi_tryton_integration-2.0.4.dist-info/top_level.txt
fastapi_tryton_integration-2.0.4.dist-info/RECORD
