Metadata-Version: 2.4
Name: fastapi_tryton_integration
Version: 2.0.4
Summary: FastAPI connection module for Tryton ERP
Author: Solutema SRL
License: GNU GENERAL PUBLIC LICENSE
Keywords: fastapi,tryton,erp,integration,python
Classifier: Environment :: Web Environment
Classifier: Framework :: Tryton
Classifier: Framework :: FastAPI
Classifier: Intended Audience :: Developers
Classifier: License :: OSI Approved :: GNU General Public License (GPL)
Classifier: Operating System :: OS Independent
Classifier: Programming Language :: Python :: 3.10
Classifier: Programming Language :: Python :: 3.11
Classifier: Programming Language :: Python :: 3.12
Classifier: Topic :: Internet :: WWW/HTTP :: Dynamic Content
Classifier: Topic :: Software Development :: Libraries :: Python Modules
Requires-Python: >=3.10
License-File: LICENSE
Requires-Dist: uvicorn
Requires-Dist: fastapi==0.115.6
Requires-Dist: pydantic==1.10.19
Requires-Dist: trytond~=6.0.0
Dynamic: license-file
